.gitignore
MANIFEST.in
README.rst
setup.py
girder_openid/__init__.py
girder_openid/constants.py
girder_openid/models.py
girder_openid/rest.py
girder_openid/store.py
girder_openid.egg-info/PKG-INFO
girder_openid.egg-info/SOURCES.txt
girder_openid.egg-info/dependency_links.txt
girder_openid.egg-info/entry_points.txt
girder_openid.egg-info/not-zip-safe
girder_openid.egg-info/requires.txt
girder_openid.egg-info/top_level.txt
girder_openid/web_client/main.js
girder_openid/web_client/package.json
girder_openid/web_client/stylesheets/openIdLoginView.styl
girder_openid/web_client/templates/openIdLoginView.pug
girder_openid/web_client/views/LoginView.js
girder_openid/web_client/views/OpenIdLoginView.js