Metadata-Version: 2.1
Name: girder-openid
Version: 0.1.0
Summary: Allows users to log into Girder using OpenID 1.0 providers
Home-page: https://github.com/girder/openid
Author: Zach Mullen
Author-email: zach.mullen@kitware.com
License: Apache Software License 2.0
Keywords: girder-plugin,openid
Platform: UNKNOWN
Classifier: Development Status :: 2 - Pre-Alpha
Classifier: License :: OSI Approved :: Apache Software License
Classifier: Natural Language :: English
Classifier: Programming Language :: Python :: 3
Classifier: Programming Language :: Python :: 3.5
Classifier: Programming Language :: Python :: 3.6
Classifier: Programming Language :: Python :: 3.7
